{
	"configurations" : 
	[
		{
			"directories" : 
			[
				{
					"build" : ".",
					"jsonFile" : "directory-.-Debug-d0094a50bb2071803777.json",
					"minimumCMakeVersion" : 
					{
						"string" : "3.27"
					},
					"projectIndex" : 0,
					"source" : ".",
					"targetIndexes" : 
					[
						0
					]
				}
			],
			"name" : "Debug",
			"projects" : 
			[
				{
					"directoryIndexes" : 
					[
						0
					],
					"name" : "Packbits",
					"targetIndexes" : 
					[
						0
					]
				}
			],
			"targets" : 
			[
				{
					"directoryIndex" : 0,
					"id" : "packbits::@6890427a1f51a3e7e1df",
					"jsonFile" : "target-packbits-Debug-d41c4ce07d21d85d07a4.json",
					"name" : "packbits",
					"projectIndex" : 0
				}
			]
		}
	],
	"kind" : "codemodel",
	"paths" : 
	{
		"build" : "C:/Users/nicol/Desktop/data_processing/Packbits/cmake-build-debug",
		"source" : "C:/Users/nicol/Desktop/data_processing/Packbits"
	},
	"version" : 
	{
		"major" : 2,
		"minor" : 6
	}
}
